MANIFEST.in
README.md
setup.cfg
setup.py
PCM2Wav/PCM2Wav.py
PCM2Wav/__init__.py
PCM2Wav.egg-info/PKG-INFO
PCM2Wav.egg-info/SOURCES.txt
PCM2Wav.egg-info/dependency_links.txt
PCM2Wav.egg-info/requires.txt
PCM2Wav.egg-info/top_level.txt
PCM2Wav/PCM/PCM.py
PCM2Wav/PCM/__init__.py
PCM2Wav/PCM/logic/__init__.py
PCM2Wav/PCM/logic/saleae.py
PCM2Wav/PCM/logic/sigrok.py