Metadata-Version: 1.1
Name: PCM2Wav
Version: 1.2
Summary: A PCM data to Wav audio format converter
Home-page: https://github.com/roel0/PCM2Wav-py
Author: Roel Postelmans
Author-email: postelmansroel@gmail.com
License: GPL-2.0
Keywords: PCM I2S sigrok saleae wav audio
Platform: UNKNOWN
Classifier: Intended Audience :: Developers
Classifier: Programming Language :: Python
Classifier: Programming Language :: Python :: 2
Classifier: Programming Language :: Python :: 2.7
Classifier: Programming Language :: Python :: 3
Classifier: Programming Language :: Python :: 3.6
Classifier: Operating System :: OS Independent
Classifier: Topic :: Scientific/Engineering
Classifier: Topic :: Software Development :: Embedded Systems
Classifier: Topic :: Utilities
